alfipy/AlfiConfig.py
alfipy/AlfiConfigFromCertificateAndPrivateKey.py
alfipy/AlfiConstants.py
alfipy/ApiGremlinService.py
alfipy/ApplicationCoordinates.py
alfipy/ApplicationType.py
alfipy/Atomic.py
alfipy/BoundedConcurrentSet.py
alfipy/Client.py
alfipy/ContextAwareGremlinCoordinatesProvider.py
alfipy/Coordinates.py
alfipy/EnvironmentVariableConfigurationProvider.py
alfipy/EnvironmentVariableConfigurationResolver.py
alfipy/EnvironmentVariableCoordinatesProvider.py
alfipy/EnvironmentVariableNameKeys.py
alfipy/EnvironmentVariableProvider.py
alfipy/ExactField.py
alfipy/Exceptions.py
alfipy/ExperimentImpact.py
alfipy/ExperimentResponse.py
alfipy/Field.py
alfipy/GremlinALFICrypto.py
alfipy/GremlinApiClient.py
alfipy/GremlinApiClientFactory.py
alfipy/GremlinApiClientResolver.py
alfipy/GremlinApiHttpClient.py
alfipy/GremlinApiRequestsClient.py
alfipy/GremlinApiUrllib3Client.py
alfipy/GremlinConfiguration.py
alfipy/GremlinConfigurationResolver.py
alfipy/GremlinCoordinatesProvider.py
alfipy/GremlinHttpProxy.py
alfipy/GremlinInterceptor.py
alfipy/GremlinService.py
alfipy/GremlinServiceFactory.py
alfipy/GremlinTime.py
alfipy/Impact.py
alfipy/ImpactProvider.py
alfipy/ImpactType.py
alfipy/PassthroughGremlinService.py
alfipy/QueryField.py
alfipy/QueryModel.py
alfipy/QueryTypeProvider.py
alfipy/SystemGremlinConfigurationResolver.py
alfipy/TestGremlinCoordinatesProvider.py
alfipy/TrafficAndImpactProvider.py
alfipy/TrafficCoordinates.py
alfipy/TrafficQuery.py
alfipy/TrafficQueryAndImpact.py
alfipy/TrafficQueryProvider.py
alfipy/TrafficType.py
alfipy/TypeProvider.py
alfipy/TypedAlfiModel.py
alfipy/Version.py
alfipy/WildcardField.py
alfipy/__init__.py
alfipy/alfi_messages_pb2.py
tests/__init__.py
tests/test_all.py
tests/test_api_gremlin_service.py
tests/test_application_coordinates.py
tests/test_atomic.py
tests/test_bounded_concurrent_set.py
tests/test_client.py
tests/test_config.py
tests/test_config_wkeys.py
tests/test_context_aware_gremlin_coordinates_provider.py
alfipy-0.0.1.dist-info/LICENSE.txt
alfipy-0.0.1.dist-info/METADATA
alfipy-0.0.1.dist-info/WHEEL
alfipy-0.0.1.dist-info/top_level.txt
alfipy-0.0.1.dist-info/RECORD
